nepali_date/__init__.py
nepali_date/__main__.py
nepali_date/date.py
nepali_date/data/__init__.py
nepali_date/data/calendar_bs.csv
nepali_date/data/translations.json
nepali_date-2.0.5.dist-info/METADATA
nepali_date-2.0.5.dist-info/WHEEL
nepali_date-2.0.5.dist-info/top_level.txt
nepali_date-2.0.5.dist-info/RECORD
