Metadata-Version: 2.1
Name: nepali-date
Version: 2.0.5
Summary: Nepali Date API
Home-page: https://github.com/arneec/nepali-date
Author: Amit Garu
Author-email: amitgaru2@gmail.com
License: MIT
Keywords: Nepali,BS,B.S,Date,Nepal,Bikram,Sambat,Year,Month,Day,calendar,nepali-calendar,nepali-date
Platform: UNKNOWN
Classifier: Programming Language :: Python :: 3
Classifier: License :: OSI Approved :: MIT License
Classifier: Operating System :: OS Independent
Requires-Python: >=3.5
